mobile_use/__init__.py
mobile_use/action.py
mobile_use/adb_utils.py
mobile_use/environ.py
mobile_use/logger.py
mobile_use/scheme.py
mobile_use/utils.py
mobile_use/vlm.py
mobile_use/webui.py
mobile_use/agents/__init__.py
mobile_use/agents/agent_qwen.py
mobile_use/agents/agent_qwen_with_summary.py
mobile_use/agents/agent_react.py
mobile_use/agents/agent_uitars.py
mobile_use/agents/base.py
mobile_use/agents/multi_agent.py
mobile_use/agents/sub_agent.py
mobile_use-0.3.0.dist-info/METADATA
mobile_use-0.3.0.dist-info/WHEEL
mobile_use-0.3.0.dist-info/licenses/LICENSE
mobile_use-0.3.0.dist-info/RECORD
