Metadata-Version: 2.4
Name: mobile-use
Version: 0.3.0
Summary: Mobile Use​: Automate your mobile with AI - Any app, any task.
Author: zhoujiamu, moxiaoyun, lining, pengqiuying, quxiangmou
License: MIT License
License-File: LICENSE
Requires-Python: >=3.10
Requires-Dist: absl-py==2.1.0
Requires-Dist: adbutils<3.0.0,>=2.8.0
Requires-Dist: colorama>=0.4.6
Requires-Dist: dm-env==1.6
Requires-Dist: fuzzywuzzy==0.18.0
Requires-Dist: google-generativeai
Requires-Dist: gradio
Requires-Dist: grpcio==1.71.0
Requires-Dist: immutabledict==4.2.1
Requires-Dist: ipython==8.32.0
Requires-Dist: jsonschema==4.17.3
Requires-Dist: matplotlib
Requires-Dist: numpy==1.26.3
Requires-Dist: openai==1.63.0
Requires-Dist: opencv-python==4.11.0.86
Requires-Dist: pandas==2.1.4
Requires-Dist: portpicker==1.6.0
Requires-Dist: protobuf==5.29.0
Requires-Dist: pydub==0.25.1
Requires-Dist: pygame==2.6.1
Requires-Dist: pyregister==0.0.1
Requires-Dist: python-dotenv<2.0.0,>=1.0.1
Requires-Dist: python-levenshtein==0.26.1
Requires-Dist: requests==2.32.3
Requires-Dist: scikit-image
Requires-Dist: setuptools
Requires-Dist: tenacity==9.0.0
Requires-Dist: termcolor==2.5.0
Provides-Extra: dev
Requires-Dist: pytest<9,>=8.1.1; extra == 'dev'
